mp8833/__init__.py
mp8833/mp8833.py
mp8833-0.0.1.dist-info/DESCRIPTION.rst
mp8833-0.0.1.dist-info/METADATA
mp8833-0.0.1.dist-info/RECORD
mp8833-0.0.1.dist-info/WHEEL
mp8833-0.0.1.dist-info/metadata.json
mp8833-0.0.1.dist-info/top_level.txt
